brainrot/__init__.py
brainrot/__main__.py
brainrot/brainrot_functions.py
brainrot_generator-0.1.8.dist-info/licenses/LICENSE
brainrot_generator-0.1.8.dist-info/METADATA
brainrot_generator-0.1.8.dist-info/WHEEL
brainrot_generator-0.1.8.dist-info/top_level.txt
brainrot_generator-0.1.8.dist-info/RECORD
