Metadata-Version: 2.4
Name: brainrot-generator
Version: 0.1.8
Summary: A fun package for generating random brainrot content and text transformations
Author-email: Vladimir Kartamyshev <vnk3247@nyu.edu>, Tony Liu <tl3608@nyu.edu>, Giulia Carvalho <gbc9191@nyu.edu>, Clarissa Choi <csc9610@nyu.edu>
License-Expression: MIT
Project-URL: Homepage, https://github.com/software-students-spring2025/3-python-package-5bigbooms
Classifier: Programming Language :: Python :: 3
Classifier: Programming Language :: Python :: 3.8
Classifier: Programming Language :: Python :: 3.9
Classifier: Operating System :: OS Independent
Requires-Python: >=3.8
License-File: LICENSE
Requires-Dist: pytest>=7.0.0
Dynamic: license-file
